CHANGES.txt
MANIFEST.in
README.rst
setup.py
tomcom/__init__.py
tomcom.patch.getbrowser.egg-info/PKG-INFO
tomcom.patch.getbrowser.egg-info/SOURCES.txt
tomcom.patch.getbrowser.egg-info/dependency_links.txt
tomcom.patch.getbrowser.egg-info/entry_points.txt
tomcom.patch.getbrowser.egg-info/namespace_packages.txt
tomcom.patch.getbrowser.egg-info/not-zip-safe
tomcom.patch.getbrowser.egg-info/requires.txt
tomcom.patch.getbrowser.egg-info/top_level.txt
tomcom/patch/__init__.py
tomcom/patch/getbrowser/__init__.py
tomcom/patch/getbrowser/tests/__init__.py
tomcom/patch/getbrowser/tests/test_get_browser.py