Metadata-Version: 1.1
Name: tomcom.patch.getbrowser
Version: 2.13.21.2
Summary: A patch to query a browser on every context
Home-page: https://github.com/tomcom-de/tomcom.patch.getbrowser.git
Author: Tomcom GmbH
Author-email: infot@tomcom.de
License: GPL version 2
Keywords: tomcom hook get_browser zope2
Platform: Any
Classifier: Development Status :: 5 - Production/Stable
Classifier: Environment :: Web Environment
Classifier: Framework :: Zope2
Classifier: Intended Audience :: Other Audience
Classifier: Intended Audience :: System Administrators
Classifier: License :: OSI Approved :: GNU General Public License (GPL)
Classifier: Operating System :: OS Independent
Classifier: Programming Language :: Python
Classifier: Topic :: Internet :: WWW/HTTP :: Site Management :: Link Checking
